hw3/verichip.sv
module verichip (input logic clk,                       // system clock
                 input logic rst_b,                     // chip reset
                 input logic export_disable,            // disable features
                 output logic interrupt_1,              // first interrupt
                 output logic interrupt_2,              // second interrupt

                 input logic maroon,                    // maroon state machine input
                 input logic gold,                      // gold state machine input

                 input logic chip_select,               // target of r/w
                 input logic [6:0] address,             // address bus
                 input logic [1:0] byte_en,             // write byte enables
                 input logic       rw_,                 // read/write
                 input logic [15:0] data_in,            // input data bus

                 output logic [15:0] data_out);          // output data bus

localparam VCHIP_ALU_VER = 4'h2;    // current ALU version
localparam VCHIP_MAJ_VER = 4'h1;
localparam VCHIP_MIN_VER = 4'h0;

localparam VCHIP_STATE_RESET = 4'h0;
localparam VCHIP_STATE_NORM  = 4'h1;
localparam VCHIP_STATE_ERR   = 4'h2;
localparam VCHIP_STATE_EXP   = 4'h8;
localparam VCHIP_STATE_LOST  = 4'hF;

localparam VCHIP_ADDR_VER = 7'h00;
localparam VCHIP_ADDR_STA = 7'h04;
localparam VCHIP_ADDR_CMD = 7'h08;
localparam VCHIP_ADDR_CON = 7'h0C;
localparam VCHIP_ADDR_LFT = 7'h10;
localparam VCHIP_ADDR_RGT = 7'h14;
localparam VCHIP_ADDR_ALU = 7'h18;

localparam VCHIP_CMD_NONE = 4'h0;

localparam VCHIP_STA_INT2 = 9;      // bit position of interrupt 2
localparam VCHIP_STA_INT1 = 8;      // bit position of interrupt 1

localparam VCHIP_CMD_LEFT = 3;      // left bit of command in command register
localparam VCHIP_CMD_VAL  = 15;     // valid bit
localparam VCHIP_CMD_NON = 0;
localparam VCHIP_CMD_ADD = 1;
localparam VCHIP_CMD_SUB = 2;
localparam VCHIP_CMD_MVL = 3;
localparam VCHIP_CMD_MVR = 4;
localparam VCHIP_CMD_SWA = 5;
localparam VCHIP_CMD_SHL = 6;
localparam VCHIP_CMD_SHR = 7;
localparam VCHIP_LAST_CMD = 7;
localparam VCHIP_LAST_EXP_CMD = 2;

// Version Register flops
logic export_dis;                   // if 1, export disable is 1
logic [15:0] version_reg;           // concat of bits

// Status Regiser flops
logic        int2;                  // interrupt 2
logic        int1;                  // interrupt 1
logic [3:0]  state;                 // state machine state
logic [15:0] status_reg;            // concat of bits
logic [3:0]  next_state;            // next state machine state

// Command Register flops
logic        valid;                 // command is valid
logic [3:0]  cmd;                   // the command
logic [15:0] cmd_reg;               // concat of bits
logic        bad_exp_cmd;           // bad command when export disable asserted
logic        bad_cmd;               // undefined command

// Configuration Register flops
logic int2_en;                      // enable interrupt 2
logic int1_en;                      // enable interrupt 1
logic [15:0] con_reg;               // concat of bits

// ALU Registers
logic [15:0] alu_left;              // left input
logic [15:0] alu_right;             // right input
logic [15:0] alu_out;               // result
logic        overflow;              // bad add/sub
logic [15:0] alu_result;            // result
logic [15:0] next_left;             // value from ALU to load
logic [15:0] next_right;            // value from ALU to load
logic        load_left;             // load value from ALU
logic        load_right;            // load value from ALU

logic [15:0] data_out_tmp;          // read data

always_ff @ ( posedge clk or negedge rst_b )
begin
  if ( !rst_b )
  begin
     export_dis <= export_disable;
     state      <= VCHIP_STATE_RESET;
     alu_out    <= 16'h0;
  end // if ( !rst_b )
  else
  begin
     export_dis <= export_disable;
     state <= next_state;
     alu_out <= alu_result;
  end // else: !if( !rst_b )
end

assign bad_exp_cmd = export_dis && valid && ( cmd > VCHIP_LAST_EXP_CMD );
assign bad_cmd     = valid && ( cmd > VCHIP_LAST_CMD );
assign overflow    = valid &&
                     ( ( ( cmd == VCHIP_CMD_ADD ) &&                                      // adding
                         ( ( alu_left[15] && alu_right[15] && !alu_result[15] ) ||        // two neg -> pos
                           ( !alu_left[15] && !alu_right[15] && alu_result[15] ) ) ) ||   // two pos -> neg
                        ( ( cmd == VCHIP_CMD_SUB ) &&                                     // subtracting
                          ( ( alu_left[15] && !alu_right[15] && !alu_result[15] ) ||      // neg - pos -> pos
                            ( !alu_left[15] && alu_right[15] && alu_result[15] ) ) ) );   // pos - neg -> neg

assign interrupt_1 = int1;
assign interrupt_2 = int2;

always_comb
begin
   case ( state )
     VCHIP_STATE_RESET:
     begin
        if ( !maroon && gold )
           next_state = VCHIP_STATE_NORM;
        else
           next_state = VCHIP_STATE_RESET;
     end // case: VCHIP_STATE_RESET

     VCHIP_STATE_NORM:
     begin
        if ( export_dis && valid && bad_exp_cmd )
           next_state = VCHIP_STATE_EXP;
        else if ( valid && ( bad_cmd || overflow ) )
           next_state = VCHIP_STATE_ERR;
        else
           next_state = VCHIP_STATE_NORM;
     end // case: VCHIP_STATE_NORM

     VCHIP_STATE_ERR:
     begin
        if ( maroon && !gold )
           next_state = VCHIP_STATE_NORM;
        else
           next_state = VCHIP_STATE_ERR;
     end // case: VCHIP_STATE_ERR

     VCHIP_STATE_EXP:
     begin
        next_state = VCHIP_STATE_EXP;
     end // case: VCHIP_STATE_EXP

     default:
     begin
        next_state = VCHIP_STATE_LOST;
     end // case: default

   endcase // case ( state )
end // always_comb

always_ff @ ( posedge clk or negedge rst_b )
begin
  if ( !rst_b )
  begin
     int1       <= 1'b0;
  end // if ( !rst_b )
  else if ( int1_en && ( state == VCHIP_STATE_NORM ) && valid &&
            ( bad_cmd || overflow ) )
  begin
     int1 <= 1'b1;
  end // if ( ( state == VCHIP_STATE_NORM ) && valid &&...
  else if ( chip_select && !rw_ && ( address == VCHIP_ADDR_STA ) && byte_en[1] )
  begin
     if ( data_in[VCHIP_STA_INT1] )
        int1 <= 1'b0;
  end // else: !if( !rst_b )
end // always_ff @ ( posedge clk or negedge rst_b )

always_ff @ ( posedge clk or negedge rst_b )
begin
  if ( !rst_b )
  begin
     int2       <= 1'b0;
  end // if ( !rst_b )
  else if ( int2_en && ( state == VCHIP_STATE_NORM ) && valid && bad_exp_cmd )
  begin
     int2 <= 1'b1;
  end // if ( ( state == VCHIP_STATE_NORM ) && valid &&...
  else if ( chip_select && !rw_ && ( address == VCHIP_ADDR_STA ) && byte_en[1] )
  begin
     if ( data_in[VCHIP_STA_INT2] )
        int2 <= 1'b0;
  end // else: !if( !rst_b )
end // always_ff @ ( posedge clk or negedge rst_b )

always_ff @ ( posedge clk or negedge rst_b )
begin
  if ( !rst_b )
  begin
     valid <= 1'b0;
     cmd <= VCHIP_CMD_NONE;
  end // if ( !rst_b )
  else if ( next_state == VCHIP_STATE_EXP )
  begin
     valid <= 1'b0;
     cmd <= VCHIP_CMD_NONE;
  end // if ( next_state == VCHIP_STATE_EXP )
  else if ( state == VCHIP_STATE_ERR )
  begin
     valid <= 1'b0;
     cmd <= cmd;
  end // if ( state == VCHIP_STATE_ERR )
  else if ( chip_select && !rw_ && ( address == VCHIP_ADDR_CMD ) )
  begin
     valid <= data_in[VCHIP_CMD_VAL] && byte_en[1];
     if ( byte_en[0] )
        cmd <= data_in[VCHIP_CMD_LEFT:0];
  end // if ( chip_select && !rw_ && ( address == VCHIP_ADDR_CMD ) )
  else
  begin
     valid <= 1'b0;
  end // else: !if( chip_select && !rw_ && ( address == VCHIP_ADDR_CMD ) )
end // always_ff @ ( posedge clk or negedge rst_b )

always_ff @ ( posedge clk or negedge rst_b )
begin
  if ( !rst_b )
  begin
     int2_en    <= 1'b0;
     int1_en    <= 1'b0;
  end // if ( !rst_b )
  else if ( next_state == VCHIP_STATE_EXP )
  begin
     int2_en <= 1'b0;
     int1_en <= 1'b0;
  end // if ( next_state == VCHIP_STATE_EXP )
  else if ( state == VCHIP_STATE_ERR )
  begin
     int2_en <= int2_en;
     int1_en <= int1_en;
  end // if ( state == VCHIP_STATE_ERR )
  else if ( chip_select && !rw_ && ( address == VCHIP_ADDR_CON ) && byte_en[1] )
  begin
     int2_en <= data_in[VCHIP_STA_INT2];
     int1_en <= data_in[VCHIP_STA_INT1];
  end // else: !if( !rst_b )
end // always_ff @ ( posedge clk or negedge rst_b )

always_ff @ ( posedge clk or negedge rst_b )
begin
  if ( !rst_b )
  begin
     alu_left <= 16'h0;
  end // if ( !rst_b )
  else if ( next_state == VCHIP_STATE_EXP )
  begin
     alu_left <= 16'h0;
  end // if ( next_state == VCHIP_STATE_EXP )
  else if ( state == VCHIP_STATE_ERR )
  begin
     alu_left <= alu_left;
  end // if ( state == VCHIP_STATE_ERR )
  else if ( chip_select && !rw_ && ( address == VCHIP_ADDR_LFT ) )
  begin
     if ( byte_en[0] )
        alu_left[7:0] <= data_in[7:0];
     if ( byte_en[1] )
        alu_left[15:8] <= data_in[15:8];
  end // if ( chip_select && !rw_ && ( address == VCHIP_ADDR_LFT ) )
  else if ( load_left )
  begin
     alu_left <= next_left;
  end // if ( load_left )
end // always_ff @ ( posedge clk or negedge rst_b )

always_ff @ ( posedge clk or negedge rst_b )
begin
  if ( !rst_b )
  begin
     alu_right <= 16'h0;
  end // if ( !rst_b )
  else if ( next_state == VCHIP_STATE_EXP )
  begin
     alu_right <= 16'h0;
  end // if ( next_state == VCHIP_STATE_EXP )
  else if ( state == VCHIP_STATE_ERR )
  begin
     alu_right <= alu_right;
  end // if ( state == VCHIP_STATE_ERR )
  else if ( chip_select && !rw_ && ( address == VCHIP_ADDR_RGT ) )
  begin
     if ( byte_en[0] )
        alu_right[7:0] <= data_in[7:0];
     if ( byte_en[1] )
        alu_right[15:8] <= data_in[15:8];
  end // if ( chip_select && !rw_ && ( address == VCHIP_ADDR_LFT ) )
  else if ( load_right )
  begin
     alu_right <= next_right;
  end // if ( load_right )
end // always_ff @ ( posedge clk or negedge rst_b )

always_comb
begin
  if ( ( next_state == VCHIP_STATE_EXP ) && ( address != VCHIP_ADDR_STA ) )
     data_out = 16'h0;
  else if ( chip_select )
     data_out = data_out_tmp;
  else
     data_out = 16'h0;
end // always_comb

assign version_reg = { export_dis, 3'h0, VCHIP_ALU_VER, VCHIP_MAJ_VER, VCHIP_MIN_VER };
assign status_reg  = { 6'h0, int2, int1, 4'h0, state };
assign cmd_reg     = { valid, 11'h0, cmd };
assign con_reg     = { 6'h0, int2_en, int1_en, 8'h0 };

always_comb
begin
  case ( address )
    VCHIP_ADDR_VER: data_out_tmp = version_reg;
    VCHIP_ADDR_STA: data_out_tmp = status_reg;
    VCHIP_ADDR_CMD: data_out_tmp = cmd_reg;
    VCHIP_ADDR_CON: data_out_tmp = con_reg;
    VCHIP_ADDR_LFT: data_out_tmp = alu_left;
    VCHIP_ADDR_RGT: data_out_tmp = alu_right;
    VCHIP_ADDR_ALU: data_out_tmp = alu_out;

    default: data_out_tmp = 16'h0;
  endcase // case ( address )
end // always_comb

// build the ALU
always_comb
begin
   if ( next_state == VCHIP_STATE_EXP )
   begin
      alu_result = 16'h0;
      load_left = 1'b0;
      load_right = 1'b0;
      next_left = 16'h0;
      next_right = 16'h0;
   end // if ( next_state == VCHIP_STATE_EXP )

   else if ( ( state != VCHIP_STATE_NORM ) || !valid || bad_cmd )
   begin
      alu_result = alu_out;
      load_left = 1'b0;
      load_right = 1'b0;
      next_left = 16'h0;
      next_right = 16'h0;
   end // if ( ( state != VCHIP_STATE_NORM ) || !valid || bad_cmd )

   else
   begin
      case ( cmd )
        VCHIP_CMD_NONE:
        begin
           alu_result = alu_out;
           load_left = 1'b0;
           load_right = 1'b0;
           next_left = 16'h0;
           next_right = 16'h0;
        end // case: VCHIP_CMD_NONE

        VCHIP_CMD_ADD:
        begin
           alu_result = alu_left + alu_right;
           load_left = 1'b0;
           load_right = 1'b0;
           next_left = 16'h0;
           next_right = 16'h0;
        end // case: VCHIP_CMD_ADD

        VCHIP_CMD_SUB:
        begin
           alu_result = alu_left - alu_right;
           load_left = 1'b0;
           load_right = 1'b0;
           next_left = 16'h0;
           next_right = 16'h0;
        end // case: VCHIP_CMD_SUB

        VCHIP_CMD_MVL:   // move out to left
        begin
           alu_result = alu_out;
           load_left = 1'b1;
           load_right = 1'b0;
           next_left = alu_out;
           next_right = 16'h0;
        end // case: VCHIP_CMD_MVL

        VCHIP_CMD_MVR:   // move out to right
        begin
           alu_result = alu_out;
           load_left = 1'b0;
           load_right = 1'b1;
           next_left = 16'h0;
           next_right = alu_out;
        end // case: VCHIP_CMD_MVR

        VCHIP_CMD_SWA:
        begin
           alu_result = alu_out;
           load_left = 1'b1;
           load_right = 1'b1;
           next_left = alu_right;
           next_right = alu_left;
        end // case: VCHIP_CMD_SWA

        VCHIP_CMD_SHL:
        begin
           alu_result = alu_left << alu_right;
           load_left = 1'b0;
           load_right = 1'b0;
           next_left = 16'h0;
           next_right = 16'h0;
        end // case: VCHIP_CMD_SHL

        VCHIP_CMD_SHR:
        begin
           alu_result = alu_left >> alu_right;
           load_left = 1'b0;
           load_right = 1'b0;
           next_left = 16'h0;
           next_right = 16'h0;
        end // case: VCHIP_CMD_SHR

        default:
        begin
           alu_result = alu_out;
           load_left = 1'b0;
           load_right = 1'b0;
           next_left = 16'h0;
           next_right = 16'h0;
        end // case: default
      endcase // case ( cmd )
   end // else: !if( ( state != VCHIP_STATE_NORM ) || !valid || bad_cmd )
end // always_comb

endmodule

hw3/top_verichip.sv
`timescale 1ns/1ps
// performed in 0 time

`define DISPLAY_STATE \
   $display("state: %h", verichip.state);  

`define SET_WRITE(addr,val,bytes,cs)   \
   rw_ <= 1'b0;                     \
   chip_select <= cs;               \
   byte_en <= bytes;                \
   address <= addr;                 \
   data_in <= val;

// also in 0 time?
`define SET_READ(addr,cs)           \
   rw_ <= 1'b1;                     \
   chip_select <= cs;               \
   byte_en <= 2'b00;                \
   address <= addr;                 \
   data_in <= 16'h0;

// sets everything to "active"(?) values
`define CLEAR_BUS                   \
   chip_select    <= 1'b0;          \
   address        <= 7'h0;          \
   byte_en        <= 2'h0;          \
   rw_            <= 1'b1;          \
   data_in        <= 16'h0;


`define CLEAR_ALL                   \
   export_disable <= 1'b0;          \
   maroon         <= 1'b0;          \
   gold           <= 1'b0;          \
   `CLEAR_BUS

`define WRITE_REG(addr,wval,bytes,cs) \
   wait(clk == 1'b0); \
   `SET_WRITE(addr,wval,bytes,cs) \
   wait(clk == 1'b1); \
   `CLEAR_BUS \
   wait(clk == 1'b0);


`define READ_REG(addr,cs) \
   wait(clk == 1'b1); \
   `SET_READ(addr,cs) \
   wait(clk == 1'b0); \
   wait(clk == 1'b1);

//give it a value, if the data_out on the data bus is not that value, throw an error
`define CHECK_VAL(val)                                      \
   $write("[data_out, expected] = [%h, %h]", data_out, val);\
   if ( data_out != val )                                   \
      $write(" : bad read @ time: ",data_out,val,$time());  \
   $display();

`define CHECK_RW(addr,wval,exp_val,bytes,cs)    \
   `WRITE_REG(addr,wval,bytes,cs)         \
   `READ_REG(addr,cs)                     \
   //TODO can we comment out this debug output? \
   $display("data out is %h",data_out);   \
   `CHECK_VAL(exp_val)

// waits for the clock to be 0 and then asserts reset, then waits for 
// clk == 1 to deassert reset
`define CHIP_RESET                  \
   wait( clk == 1'b0 );             \
   rst_b <= 1'b0;                   \
   wait( clk == 1'b1 );             \
   rst_b <= 1'b1;

`define CHIP_NORMAL    \
   wait(clk == 1'b0);  \
   rst_b <= 1'b0;      \
   wait(clk == 1'b1);  \
   rst_b <= 1'b1;      \
   wait(clk == 1'b0);  \
                       \
   //go into normal from reset \
   maroon <= 1'b0;     \
   gold <= 1'b1;       \
   wait(clk == 1'b1);  \
   wait(clk == 1'b0);  \

`define CHIP_ERROR  \
   wait(clk == 1'b0);  \
   rst_b <= 1'b0;      \
   wait(clk == 1'b1);  \
   rst_b <= 1'b1;      \
   wait(clk == 1'b0);  \
                       \
   //go into normal from reset \
   maroon <= 1'b0;     \
   gold <= 1'b1;       \
   wait(clk == 1'b1);  \
   wait(clk == 1'b0);  \
                       \
   //set to a non-zero initial value                     \
   `CHECK_RW(VCHIP_ALU_LEFT_ADDR, 16'h1234, 16'h1234, 2'b11, 1'b1)     \
                                                         \
   //write bad command to command reg to go into error   \
   `WRITE_REG(VCHIP_CMD_ADDR, 16'h800C, 2'b11, 1'b1)     \
   wait(clk == 1'b1); wait(clk == 1'b0); //min wait to see state change debug output   \

   `define CHIP_EXP_VIO    \
                        \
   wait(clk == 1'b0);   \
   rst_b <= 1'b0;       \
   wait(clk == 1'b1);   \
   rst_b <= 1'b1;       \
   wait(clk == 1'b0);   \
                        \
   //go into normal from reset \
                        \
   maroon <= 1'b0;      \
   gold <= 1'b1;        \
   wait(clk == 1'b1);   \
   wait(clk == 1'b0);   \
                        \
   export_disable <= 1'b1; \
                        \
   //write restricted cmd to command reg to go into error   \
   //(even invalid commands are restricted)                 \
   `WRITE_REG(VCHIP_CMD_ADDR, 16'h8008, 2'b11, 1'b1)                                   \
   wait(clk == 1'b1); wait(clk == 1'b0); //min wait to see state change debug output   \


module top_verichip ();

logic clk;                       // system clock
logic rst_b;                     // chip reset
logic export_disable;            // disable features
logic interrupt_1;               // first interrupt
logic interrupt_2;               // second interrupt

logic maroon;                    // maroon state machine input
logic gold;                      // gold state machine input

logic chip_select;               // target of r/w
logic [6:0] address;             // address bus
logic [1:0] byte_en;             // write byte enables
logic       rw_;                 // read/write
logic [15:0] data_in;            // input data bus

logic [15:0] data_out;           // output data bus

localparam VCHIP_VER_ADDR       = 7'h00;
localparam VCHIP_STA_ADDR       = 7'h04;
localparam VCHIP_CMD_ADDR       = 7'h08;
localparam VCHIP_CON_ADDR       = 7'h0C;
localparam VCHIP_ALU_LEFT_ADDR  = 7'h10;
localparam VCHIP_ALU_RIGHT_ADDR = 7'h14;
localparam VCHIP_ALU_OUT_ADDR   = 7'h18;

localparam VCHIP_ALU_VALID = 16'h8000;
localparam VCHIP_ALU_ADD   = 16'h0001;
localparam VCHIP_ALU_SUB   = 16'h0002;
localparam VCHIP_ALU_MVL   = 16'h0003;
localparam VCHIP_ALU_MVR   = 16'h0004;
localparam VCHIP_ALU_SWA   = 16'h0005;
localparam VCHIP_ALU_SHL   = 16'h0006;
localparam VCHIP_ALU_SHR   = 16'h0007;

initial
begin
   clk <= 1'b0;
   while ( 1 )
   begin
      #5 clk <= 1'b1;
      #5 clk <= 1'b0;
   end
end
/////////////////////////////////////////////////////////////////////////////////////
// need to test all byte enables, do it with a for loop and a case statement
// test writing regisers, test address 50 and ensure nothing is written to ALU_left,
// which is address 10

///////////////////////////////////////////////////////////////////////////////////// 
reg [15:0] stim_array [4];
reg [15:0] bit_mask_array [4];
initial
begin
   `CLEAR_ALL
   `CHIP_RESET

stim_array = {16'hFFFF, 16'hAAAA, 16'h5555, 16'h0000};
bit_mask_array = {16'h0000, 16'h00FF, 16'hFF00, 16'hFFFF};

$display("\n \n \n");
`DISPLAY_STATE

$display("calling `CHIP_RESET...");
`CHIP_RESET
`DISPLAY_STATE
for (int _be = 0; _be < 4; _be ++) begin
   for (int i = 0; i < 4; i++) begin
      //$display("macro args: %h, %h", stim_array[i],stim_array[i] & bit_mask_array[_be]); 
      `CHECK_RW(VCHIP_ALU_LEFT_ADDR, stim_array[i], (stim_array[i] & bit_mask_array[_be]), _be, 1'b1)
   end
end
// YOUR STIMULUS GOES HERE!

$display("\n \n \n");
`DISPLAY_STATE

$display("calling `CHIP_NORMAL...");
`CHIP_NORMAL
`DISPLAY_STATE
for (int _be = 0; _be < 4; _be ++) begin
   for (int i = 0; i < 4; i++) begin
      //$display("macro args: %h, %h", stim_array[i],stim_array[i] & bit_mask_array[_be]); 
      `CHECK_RW(VCHIP_ALU_LEFT_ADDR, stim_array[i], (stim_array[i] & bit_mask_array[_be]), _be, 1'b1)
   end
end

//set initial value


$display("\n \n \n");
`DISPLAY_STATE 

$display("calling `CHIP_ERROR...");
`CHIP_ERROR
`DISPLAY_STATE
for (int _be = 0; _be < 4; _be ++)
   for (int i = 0; i < 4; i++) begin
      //$display("macro args: %h, %h", stim_array[i],stim_array[i] & bit_mask_array[_be]); 
      `CHECK_RW(VCHIP_ALU_LEFT_ADDR, stim_array[i], 16'h1234, _be, 1'b1)
   end

   
$display("\n \n \n");
`DISPLAY_STATE   

$display("calling `CHIP_EXP_VIO...");
`CHIP_EXP_VIO
`DISPLAY_STATE
for (int _be = 0; _be < 4; _be ++)
   for (int i = 0; i < 4; i++) begin
      //$display("macro args: %h, %h", stim_array[i],stim_array[i] & bit_mask_array[_be]); 
      `CHECK_RW(VCHIP_ALU_LEFT_ADDR, stim_array[i], 16'h0000, _be, 1'b1)
   end


   $finish;
end // initial begin


verichip verichip (.clk           ( clk            ),    // system clock
                   .rst_b         ( rst_b          ),    // chip reset
                   .export_disable( export_disable ),    // disable features
                   .interrupt_1   ( interrupt_1    ),    // first interrupt
                   .interrupt_2   ( interrupt_2    ),    // second interrupt
 
                   .maroon        ( maroon         ),    // maroon state machine input
                   .gold          ( gold           ),    // gold state machine input

                   .chip_select   ( chip_select    ),    // target of r/w
                   .address       ( address        ),    // address bus
                   .byte_en       ( byte_en        ),    // write byte enables
                   .rw_           ( rw_            ),    // read/write
                   .data_in       ( data_in        ),    // data bus

                   .data_out      ( data_out       ) );  // output data bus

initial begin
  $dumpfile("dump.vcd");
  $dumpvars();
end
endmodule

hw3/dump.vcd
$date
	Wed Mar  4 22:29:55 2026
$end
$version
	Questa Intel Starter FPGA Edition Version 2024.3
$end
$timescale
	1ps
$end

$scope module top_verichip $end
$var parameter 7 ! VCHIP_VER_ADDR $end
$var parameter 7 " VCHIP_STA_ADDR $end
$var parameter 7 # VCHIP_CMD_ADDR $end
$var parameter 7 $ VCHIP_CON_ADDR $end
$var parameter 7 % VCHIP_ALU_LEFT_ADDR $end
$var parameter 7 & VCHIP_ALU_RIGHT_ADDR $end
$var parameter 7 ' VCHIP_ALU_OUT_ADDR $end
$var parameter 16 ( VCHIP_ALU_VALID $end
$var parameter 16 ) VCHIP_ALU_ADD $end
$var parameter 16 * VCHIP_ALU_SUB $end
$var parameter 16 + VCHIP_ALU_MVL $end
$var parameter 16 , VCHIP_ALU_MVR $end
$var parameter 16 - VCHIP_ALU_SWA $end
$var parameter 16 . VCHIP_ALU_SHL $end
$var parameter 16 / VCHIP_ALU_SHR $end
$var reg 1 0 clk $end
$var reg 1 1 rst_b $end
$var reg 1 2 export_disable $end
$var reg 1 3 interrupt_1 $end
$var reg 1 4 interrupt_2 $end
$var reg 1 5 maroon $end
$var reg 1 6 gold $end
$var reg 1 7 chip_select $end
$var reg 7 8 address [6:0] $end
$var reg 2 9 byte_en [1:0] $end
$var reg 1 : rw_ $end
$var reg 16 ; data_in [15:0] $end
$var reg 16 < data_out [15:0] $end

$scope module verichip $end
$var parameter 4 = VCHIP_ALU_VER $end
$var parameter 4 > VCHIP_MAJ_VER $end
$var parameter 4 ? VCHIP_MIN_VER $end
$var parameter 4 @ VCHIP_STATE_RESET $end
$var parameter 4 A VCHIP_STATE_NORM $end
$var parameter 4 B VCHIP_STATE_ERR $end
$var parameter 4 C VCHIP_STATE_EXP $end
$var parameter 4 D VCHIP_STATE_LOST $end
$var parameter 7 E VCHIP_ADDR_VER $end
$var parameter 7 F VCHIP_ADDR_STA $end
$var parameter 7 G VCHIP_ADDR_CMD $end
$var parameter 7 H VCHIP_ADDR_CON $end
$var parameter 7 I VCHIP_ADDR_LFT $end
$var parameter 7 J VCHIP_ADDR_RGT $end
$var parameter 7 K VCHIP_ADDR_ALU $end
$var parameter 4 L VCHIP_CMD_NONE $end
$var parameter 32 M VCHIP_STA_INT2 $end
$var parameter 32 N VCHIP_STA_INT1 $end
$var parameter 32 O VCHIP_CMD_LEFT $end
$var parameter 32 P VCHIP_CMD_VAL $end
$var parameter 32 Q VCHIP_CMD_NON $end
$var parameter 32 R VCHIP_CMD_ADD $end
$var parameter 32 S VCHIP_CMD_SUB $end
$var parameter 32 T VCHIP_CMD_MVL $end
$var parameter 32 U VCHIP_CMD_MVR $end
$var parameter 32 V VCHIP_CMD_SWA $end
$var parameter 32 W VCHIP_CMD_SHL $end
$var parameter 32 X VCHIP_CMD_SHR $end
$var parameter 32 Y VCHIP_LAST_CMD $end
$var parameter 32 Z VCHIP_LAST_EXP_CMD $end
$var wire 1 [ clk $end
$var wire 1 \ rst_b $end
$var wire 1 ] export_disable $end
$var reg 1 ^ interrupt_1 $end
$var reg 1 _ interrupt_2 $end
$var wire 1 ` maroon $end
$var wire 1 a gold $end
$var wire 1 b chip_select $end
$var wire 1 c address [6] $end
$var wire 1 d address [5] $end
$var wire 1 e address [4] $end
$var wire 1 f address [3] $end
$var wire 1 g address [2] $end
$var wire 1 h address [1] $end
$var wire 1 i address [0] $end
$var wire 1 j byte_en [1] $end
$var wire 1 k byte_en [0] $end
$var wire 1 l rw_ $end
$var wire 1 m data_in [15] $end
$var wire 1 n data_in [14] $end
$var wire 1 o data_in [13] $end
$var wire 1 p data_in [12] $end
$var wire 1 q data_in [11] $end
$var wire 1 r data_in [10] $end
$var wire 1 s data_in [9] $end
$var wire 1 t data_in [8] $end
$var wire 1 u data_in [7] $end
$var wire 1 v data_in [6] $end
$var wire 1 w data_in [5] $end
$var wire 1 x data_in [4] $end
$var wire 1 y data_in [3] $end
$var wire 1 z data_in [2] $end
$var wire 1 { data_in [1] $end
$var wire 1 | data_in [0] $end
$var reg 16 } data_out [15:0] $end
$var reg 1 ~ export_dis $end
$var reg 16 !! version_reg [15:0] $end
$var reg 1 "! int2 $end
$var reg 1 #! int1 $end
$var reg 4 $! state [3:0] $end
$var reg 16 %! status_reg [15:0] $end
$var reg 4 &! next_state [3:0] $end
$var reg 1 '! valid $end
$var reg 4 (! cmd [3:0] $end
$var reg 16 )! cmd_reg [15:0] $end
$var reg 1 *! bad_exp_cmd $end
$var reg 1 +! bad_cmd $end
$var reg 1 ,! int2_en $end
$var reg 1 -! int1_en $end
$var reg 16 .! con_reg [15:0] $end
$var reg 16 /! alu_left [15:0] $end
$var reg 16 0! alu_right [15:0] $end
$var reg 16 1! alu_out [15:0] $end
$var reg 1 2! overflow $end
$var reg 16 3! alu_result [15:0] $end
$var reg 16 4! next_left [15:0] $end
$var reg 16 5! next_right [15:0] $end
$var reg 1 6! load_left $end
$var reg 1 7! load_right $end
$var reg 16 8! data_out_tmp [15:0] $end
$upscope $end
$upscope $end

$scope begin std $end
$upscope $end
$enddefinitions $end
#0
$dumpvars
00
01
02
03
04
05
06
07
b0 8
b0 9
1:
b0 ;
b0 <
0^
0_
b0 }
0~
b1000010000 !!
0"!
0#!
b0 $!
b0 %!
b0 &!
0'!
b0 (!
b0 )!
0*!
0+!
0,!
0-!
b0 .!
b0 /!
b0 0!
b0 1!
02!
b0 3!
b0 4!
b0 5!
06!
07!
b1000010000 8!
b0 !
b100 "
b1000 #
b1100 $
b10000 %
b10100 &
b11000 '
b1000000000000000 (
b1 )
b10 *
b11 +
b100 ,
b101 -
b110 .
b111 /
b10 =
b1 >
b0 ?
b0 @
b1 A
b10 B
b1000 C
b1111 D
b0 E
b100 F
b1000 G
b1100 H
b10000 I
b10100 J
b11000 K
b0 L
b1001 M
b1000 N
b11 O
b1111 P
b0 Q
b1 R
b10 S
b11 T
b100 U
b101 V
b110 W
b111 X
b111 Y
b10 Z
0|
0{
0z
0y
0x
0w
0v
0u
0t
0s
0r
0q
0p
0o
0n
0m
1l
0k
0j
0i
0h
0g
0f
0e
0d
0c
0b
0a
0`
0]
0\
0[
$end
#5000
10
1[
11
1\
#10000
00
0[
01
0\
#15000
10
1[
11
1\
#20000
00
0[
0:
17
b10000 8
b1111111111111111 ;
0l
1|
1{
1z
1y
1x
1w
1v
1u
1t
1s
1r
1q
1p
1o
1n
1m
1b
1e
b0 8!
#25000
10
1[
07
b0 8
1:
b0 ;
1l
0|
0{
0z
0y
0x
0w
0v
0u
0t
0s
0r
0q
0p
0o
0n
0m
0b
0e
b1000010000 8!
#30000
00
0[
#35000
10
1[
17
b10000 8
1b
1e
b0 8!
#40000
00
0[
#45000
10
1[
#50000
00
0[
0:
b1010101010101010 ;
0l
1{
1y
1w
1u
1s
1q
1o
1m
#55000
10
1[
07
b0 8
1:
b0 ;
1l
0{
0y
0w
0u
0s
0q
0o
0m
0b
0e
b1000010000 8!
#60000
00
0[
#65000
10
1[
17
b10000 8
1b
1e
b0 8!
#70000
00
0[
#75000
10
1[
#80000
00
0[
0:
b101010101010101 ;
0l
1|
1z
1x
1v
1t
1r
1p
1n
#85000
10
1[
07
b0 8
1:
b0 ;
1l
0|
0z
0x
0v
0t
0r
0p
0n
0b
0e
b1000010000 8!
#90000
00
0[
#95000
10
1[
17
b10000 8
1b
1e
b0 8!
#100000
00
0[
#105000
10
1[
#110000
00
0[
0:
0l
#115000
10
1[
07
b0 8
1:
1l
0b
0e
b1000010000 8!
#120000
00
0[
#125000
10
1[
17
b10000 8
1b
1e
b0 8!
#130000
00
0[
#135000
10
1[
#140000
00
0[
0:
b1 9
b1111111111111111 ;
0l
1|
1{
1z
1y
1x
1w
1v
1u
1t
1s
1r
1q
1p
1o
1n
1m
1k
#145000
10
1[
b11111111 /!
07
b0 8
b0 9
1:
b0 ;
1l
0|
0{
0z
0y
0x
0w
0v
0u
0t
0s
0r
0q
0p
0o
0n
0m
0k
0b
0e
b1000010000 8!
#150000
00
0[
#155000
10
1[
17
b10000 8
1b
1e
b11111111 8!
b11111111 }
b11111111 <
#160000
00
0[
#165000
10
1[
#170000
00
0[
0:
b1 9
b1010101010101010 ;
0l
1{
1y
1w
1u
1s
1q
1o
1m
1k
#175000
10
1[
b10101010 /!
07
b0 8
b0 9
1:
b0 ;
1l
0{
0y
0w
0u
0s
0q
0o
0m
0k
0b
0e
b0 }
b1000010000 8!
b0 <
#180000
00
0[
#185000
10
1[
17
b10000 8
1b
1e
b10101010 8!
b10101010 }
b10101010 <
#190000
00
0[
#195000
10
1[
#200000
00
0[
0:
b1 9
b101010101010101 ;
0l
1|
1z
1x
1v
1t
1r
1p
1n
1k
